{
  "left": {
    "topBlock": "5213",
    "block1": {
      "title": "租售统计",
      "content": [
        {
          "label": "园区总面积",
          "num": "2578.63",
          "unit": "㎡"
        },
        {
          "label": "已出租面积",
          "num": "1535",
          "unit": "㎡"
        }
      ]
    },
    "block2": {
      "title": "园区产值",
      "content": [
        {
          "label": "企业年度产值",
          "num": "2578.63"
        },
        {
          "label": "园区年度缴费",
          "num": "1535"
        },
        {
          "label": "带动结业",
          "num": "537"
        },
        {
          "label": "毕业生就业",
          "num": "351"
        }
      ]
    },
    "block3": {
      "title": "通行情况",
      "dataList": [
        {
          "info": {
            "count": 896,
            "unit": "人",
            "desc": "总人数"
          },
          "data": [
            {
              "label": "员工",
              "num": 789
            },
            {
              "label": "访客",
              "num": 83
            },
            {
              "label": "安保",
              "num": 24
            }
          ]
        },
        {
          "info": {
            "count": 261,
            "unit": "辆",
            "desc": "总车辆数"
          },
          "data": [
            {
              "label": "员工",
              "num": 215
            },
            {
              "label": "访客",
              "num": 46
            }
          ]
        }
      ]
    },
    "block4": {
      "title": "车位统计",
      "dataList": [
        {
          "title": "地上车位",
          "data": [
            {
              "label": "车位总数",
              "num": 1000
            },
            {
              "label": "空闲车位",
              "num": 723
            },
            {
              "label": "故障车位",
              "num": 5
            }
          ]
        },
        {
          "title": "地下车位",
          "data": [
            {
              "label": "车位总数",
              "num": 2000
            },
            {
              "label": "空闲车位",
              "num": 589
            },
            {
              "label": "故障车位",
              "num": 10
            }
          ]
        }
      ]
    }
  },
  "right": {
    "block1": {
      "title": "能耗详情",
      "data1": {
        "unit": "流量",
        "dayData": {
          "xData": [
            "8:00",
            "9:00",
            "10:00",
            "11:00",
            "12:00",
            "13:00"
          ],
          "seriesData": [
            [
              "400",
              "390",
              "480",
              "400",
              "330",
              "400"
            ]
          ]
        },
        "monthData": {
          "xData": [
            "24日",
            "25日",
            "26日",
            "27月",
            "28月",
            "29月"
          ],
          "seriesData": [
            [
              "2111",
              "3900",
              "4808",
              "5004",
              "3301",
              "2090"
            ]
          ]
        },
        "yearData": {
          "xData": [
            "5月",
            "6月",
            "7月",
            "8月",
            "9月",
            "10月"
          ],
          "seriesData": [
            [
              "4020",
              "4900",
              "7808",
              "6604",
              "6301",
              "5090"
            ]
          ]
        }
      },
      "data2": {
        "unit": "吨",
        "names": [
          "总用水",
          "总排污"
        ],
        "dayData": {
          "xData": [
            "8:00",
            "9:00",
            "10:00",
            "11:00",
            "12:00",
            "13:00"
          ],
          "seriesData": [
            [
              "400",
              "480",
              "330",
              "500",
              "400",
              "480"
            ],
            [
              "480",
              "400",
              "500",
              "260",
              "300",
              "390"
            ]
          ]
        },
        "monthData": {
          "xData": [
            "24日",
            "25日",
            "26日",
            "27月",
            "28月",
            "29月"
          ],
          "seriesData": [
            [
              "4000",
              "3900",
              "4808",
              "4004",
              "3301",
              "4090"
            ],
            [
              "4808",
              "4000",
              "3900",
              "3301",
              "4004",
              "4090"
            ]
          ]
        },
        "yearData": {
          "xData": [
            "5月",
            "6月",
            "7月",
            "8月",
            "9月",
            "10月"
          ],
          "seriesData": [
            [
              "4020",
              "4900",
              "6301",
              "7808",
              "6604",
              "5090"
            ],
            [
              "4020",
              "4900",
              "5090",
              "6604",
              "7808",
              "6301"
            ]
          ]
        }
      },
      "data3": {
        "dayData": [
          {
            "value": 1048,
            "name": "空调用电"
          },
          {
            "value": 735,
            "name": "新风用电"
          },
          {
            "value": 580,
            "name": "照明用电"
          },
          {
            "value": 484,
            "name": "公共用电"
          },
          {
            "value": 300,
            "name": "其他"
          }
        ],
        "monthData": [
          {
            "value": 1448,
            "name": "空调用电"
          },
          {
            "value": 1235,
            "name": "新风用电"
          },
          {
            "value": 2580,
            "name": "照明用电"
          },
          {
            "value": 1484,
            "name": "公共用电"
          },
          {
            "value": 1200,
            "name": "其他"
          }
        ],
        "yearData": [
          {
            "value": 1048,
            "name": "空调用电"
          },
          {
            "value": 1735,
            "name": "新风用电"
          },
          {
            "value": 2580,
            "name": "照明用电"
          },
          {
            "value": 4184,
            "name": "公共用电"
          },
          {
            "value": 800,
            "name": "其他"
          }
        ]
      }
    },
    "block2": {
      "title": "设备情况",
      "dataList": [
        {
          "id": 1,
          "title": "电表",
          "icon": "icon-dianbiao",
          "nums": {
            "num1": 25,
            "num2": 3
          }
        },
        {
          "id": 2,
          "title": "水表",
          "icon": "icon-shuibiao",
          "nums": {
            "num1": 56,
            "num2": 3
          }
        },
        {
          "id": 3,
          "title": "电梯",
          "icon": "icon-dianti01",
          "nums": {
            "num1": 26,
            "num2": 3
          }
        },
        {
          "id": 4,
          "title": "摄像头",
          "icon": "icon-shexiangtou",
          "nums": {
            "num1": 25,
            "num2": 3
          }
        },
        {
          "id": 5,
          "title": "消防设备",
          "icon": "icon-xiaofangshebei",
          "nums": {
            "num1": 56,
            "num2": 3
          }
        },
        {
          "id": 6,
          "title": "门禁",
          "icon": "icon-menjin",
          "nums": {
            "num1": 26,
            "num2": 3
          }
        }
      ]
    }
  },
  "content": {
    "environment": [
      {
        "key": "温度",
        "value": "15℃"
      },
      {
        "key": "湿度",
        "value": "50%"
      },
      {
        "key": "温度",
        "value": "30mg/M3"
      },
      {
        "key": "风速",
        "value": "7.2m/s"
      },
      {
        "key": "噪音",
        "value": "60dB"
      },
      {
        "key": "可燃气体",
        "value": "10mg/M3"
      }
    ],
    "building": [
      {
        "id": 1,
        "name": "A栋",
        "info": [
          {
            "title": "智慧园区A栋",
            "data": [
              {
                "key": "共计面积",
                "value": "897"
              },
              {
                "key": "已租面积",
                "value": "796"
              },
              {
                "key": "今日人数",
                "value": "123"
              },
              {
                "key": "今日访客",
                "value": "3"
              },
              {
                "key": "今日预警",
                "value": "2"
              },
              {
                "key": "今日预约",
                "value": "5"
              }
            ]
          },
          {
            "title": "电能消耗",
            "data": [
              {
                "key": "实时负荷",
                "value": "3255Kw"
              },
              {
                "key": "当日累计用电",
                "value": "1233445.68Kw/h"
              }
            ]
          },
          {
            "title": "今日人流进出",
            "data": [
              {
                "key": "进入",
                "value": "15人"
              },
              {
                "key": "出口",
                "value": "25人"
              }
            ]
          },
          {
            "title": "今日预警",
            "data": [
              {
                "key": "设备346735kb",
                "value": "1次"
              }
            ]
          },
          {
            "title": "今日给排水",
            "data": [
              {
                "key": "总用水",
                "value": "58946"
              },
              {
                "key": "排水",
                "value": "4548"
              }
            ]
          }
        ]
      },
      {
        "id": 2,
        "name": "B栋",
        "info": [
          {
            "title": "智慧园区B栋",
            "data": [
              {
                "key": "共计面积",
                "value": "897"
              },
              {
                "key": "已租面积",
                "value": "796"
              },
              {
                "key": "今日人数",
                "value": "123"
              },
              {
                "key": "今日访客",
                "value": "3"
              },
              {
                "key": "今日预警",
                "value": "2"
              },
              {
                "key": "今日预约",
                "value": "5"
              }
            ]
          },
          {
            "title": "电能消耗",
            "data": [
              {
                "key": "实时负荷",
                "value": "3255Kw"
              },
              {
                "key": "当日累计用电",
                "value": "1233445.68Kw/h"
              }
            ]
          },
          {
            "title": "今日人流进出",
            "data": [
              {
                "key": "进入",
                "value": "15人"
              },
              {
                "key": "出口",
                "value": "25人"
              }
            ]
          },
          {
            "title": "今日预警",
            "data": [
              {
                "key": "设备346735kb",
                "value": "1次"
              }
            ]
          },
          {
            "title": "今日给排水",
            "data": [
              {
                "key": "总用水",
                "value": "58946"
              },
              {
                "key": "排水",
                "value": "4548"
              }
            ]
          }
        ]
      },
      {
        "id": 3,
        "name": "C栋",
        "info": [
          {
            "title": "智慧园区C栋",
            "data": [
              {
                "key": "共计面积",
                "value": "897"
              },
              {
                "key": "已租面积",
                "value": "796"
              },
              {
                "key": "今日人数",
                "value": "123"
              },
              {
                "key": "今日访客",
                "value": "3"
              },
              {
                "key": "今日预警",
                "value": "2"
              },
              {
                "key": "今日预约",
                "value": "5"
              }
            ]
          },
          {
            "title": "电能消耗",
            "data": [
              {
                "key": "实时负荷",
                "value": "3255Kw"
              },
              {
                "key": "当日累计用电",
                "value": "1233445.68Kw/h"
              }
            ]
          },
          {
            "title": "今日人流进出",
            "data": [
              {
                "key": "进入",
                "value": "15人"
              },
              {
                "key": "出口",
                "value": "25人"
              }
            ]
          },
          {
            "title": "今日预警",
            "data": [
              {
                "key": "设备346735kb",
                "value": "1次"
              }
            ]
          },
          {
            "title": "今日给排水",
            "data": [
              {
                "key": "总用水",
                "value": "58946"
              },
              {
                "key": "排水",
                "value": "4548"
              }
            ]
          }
        ]
      },
      {
        "id": 4,
        "name": "D栋",
        "info": [
          {
            "title": "智慧园区D栋",
            "data": [
              {
                "key": "共计面积",
                "value": "897"
              },
              {
                "key": "已租面积",
                "value": "796"
              },
              {
                "key": "今日人数",
                "value": "123"
              },
              {
                "key": "今日访客",
                "value": "3"
              },
              {
                "key": "今日预警",
                "value": "2"
              },
              {
                "key": "今日预警",
                "value": "5"
              }
            ]
          },
          {
            "title": "电能消耗",
            "data": [
              {
                "key": "实时负荷",
                "value": "3255Kw"
              },
              {
                "key": "当日累计用电",
                "value": "1233445.68Kw/h"
              }
            ]
          },
          {
            "title": "今日人流进出",
            "data": [
              {
                "key": "进入",
                "value": "15人"
              },
              {
                "key": "出口",
                "value": "25人"
              }
            ]
          },
          {
            "title": "今日预警",
            "data": [
              {
                "key": "设备735346kb",
                "value": "5次"
              }
            ]
          },
          {
            "title": "今日给排水",
            "data": [
              {
                "key": "总用水",
                "value": "58946"
              },
              {
                "key": "排水",
                "value": "4548"
              }
            ]
          }
        ]
      },
      {
        "id": 5,
        "name": "F栋",
        "info": [
          {
            "title": "智慧园区F栋",
            "data": [
              {
                "key": "共计面积",
                "value": "897"
              },
              {
                "key": "已租面积",
                "value": "796"
              },
              {
                "key": "今日人数",
                "value": "123"
              },
              {
                "key": "今日访客",
                "value": "3"
              },
              {
                "key": "今日预警",
                "value": "2"
              },
              {
                "key": "今日预约",
                "value": "5"
              }
            ]
          },
          {
            "title": "电能消耗",
            "data": [
              {
                "key": "实时负荷",
                "value": "3255Kw"
              },
              {
                "key": "当日累计用电",
                "value": "1233445.68Kw/h"
              }
            ]
          },
          {
            "title": "今日人流进出",
            "data": [
              {
                "key": "进入",
                "value": "15人"
              },
              {
                "key": "出口",
                "value": "25人"
              }
            ]
          },
          {
            "title": "今日预警",
            "data": [
              {
                "key": "设备346735kb",
                "value": "1次"
              }
            ]
          },
          {
            "title": "今日给排水",
            "data": [
              {
                "key": "总用水",
                "value": "58946"
              },
              {
                "key": "排水",
                "value": "4548"
              }
            ]
          }
        ]
      }
    ]
  }
}
